MANIFEST.in
README.md
requirements.txt
requirements_dev.txt
requirements_rtd.txt
setup.cfg
setup.py
rockets/__init__.py
rockets/async_client.py
rockets/client.py
rockets/notification.py
rockets/request.py
rockets/request_error.py
rockets/request_progress.py
rockets/request_task.py
rockets/response.py
rockets/utils.py
rockets/version.py
rockets.egg-info/PKG-INFO
rockets.egg-info/SOURCES.txt
rockets.egg-info/dependency_links.txt
rockets.egg-info/requires.txt
rockets.egg-info/top_level.txt