Metadata-Version: 2.1
Name: rockets
Version: 0.1.0.dev0
Summary: Rockets python client
Home-page: https://github.com/BlueBrain/Rockets
Author: Daniel Nachbaur
Author-email: bbp-open-source@googlegroups.com
License: LGPLv3
Keywords: rockets,websocket,jsonrpc,bbp,BlueBrain
Platform: UNKNOWN
Classifier: Development Status :: 4 - Beta
Classifier: License :: OSI Approved :: GNU Lesser General Public License v3 (LGPLv3)
Classifier: Operating System :: OS Independent
Classifier: Programming Language :: Python :: 3.5
Classifier: Programming Language :: Python :: 3.6
Classifier: Programming Language :: Python :: 3.7
Classifier: Topic :: Software Development :: Libraries
Classifier: Topic :: Software Development :: Libraries :: Python Modules
